tui_snake/__init__.py
tui_snake/__main__.py
tui_snake/main.py
tui_snake/audio/corn_bite.wav
tui_snake/audio/tail_bite.wav
tui_snake/audio/wall_hit.wav
tui_snake/styles/borders.tcss
tui_snake/styles/snake.tcss
tui_snake-0.0.3.dist-info/METADATA
tui_snake-0.0.3.dist-info/WHEEL
tui_snake-0.0.3.dist-info/entry_points.txt
tui_snake-0.0.3.dist-info/RECORD
