Metadata-Version: 2.4
Name: tui-snake
Version: 0.0.3
Summary: Your Old Buddy, Snake – Slithering Through Your Terminal!
Project-URL: Homepage, https://github.com/Zimzozaur/tui-snake
Author-email: Simon Piechutowski <szymonpiechutowski@gmail.com>
Classifier: Development Status :: 2 - Pre-Alpha
Classifier: Environment :: Console
Classifier: Intended Audience :: End Users/Desktop
Classifier: Operating System :: MacOS
Classifier: Operating System :: Microsoft :: Windows :: Windows 10
Classifier: Operating System :: Microsoft :: Windows :: Windows 11
Classifier: Operating System :: POSIX :: Linux
Classifier: Programming Language :: Python
Classifier: Programming Language :: Python :: 3.12
Classifier: Topic :: Games/Entertainment :: Arcade
Requires-Python: >=3.12
Requires-Dist: pygame-ce~=2.5.0
Requires-Dist: textual
